Yuktived/__init__.py
Yuktived/data.py
Yuktived/ml.py
Yuktived/stats.py
yuktived-0.1.dist-info/LICENSE
yuktived-0.1.dist-info/METADATA
yuktived-0.1.dist-info/WHEEL
yuktived-0.1.dist-info/top_level.txt
yuktived-0.1.dist-info/RECORD
